threaded_videocapture/__init__.py
threaded_videocapture/main.py
threaded_videocapture-1.0.1.dist-info/METADATA
threaded_videocapture-1.0.1.dist-info/WHEEL
threaded_videocapture-1.0.1.dist-info/entry_points.txt
threaded_videocapture-1.0.1.dist-info/license_files/LICENSE
threaded_videocapture-1.0.1.dist-info/RECORD
