Metadata-Version: 2.1
Name: threaded-videocapture
Version: 1.0.1
Summary: OpenCV VideoCapture running in a background thread
Project-URL: Bug Tracker, https://github.com/nup002/Threaded-VideoCapture/issues
Project-URL: Homepage, https://github.com/nup002/threaded-VideoCapture
Author-email: Magne Eik Lauritzen <mag.lauritzen@gmail.com>
License: MIT License
Classifier: License :: OSI Approved :: MIT License
Classifier: Operating System :: OS Independent
Classifier: Programming Language :: Python :: 3
Requires-Python: >=3.6
Requires-Dist: opencv-python>=4.0.0.21
